{
  "menu": [
    {
      "name": "Dashboards",
      "icon": "menu-icon tf-icons bx bx-home-circle",
      "slug": "dashboard",
      "url": "/",
      "roles": [
        "admin",
        "client"
      ]
    },
    {
      "menuHeader": "Pages",
      "roles": [
        "admin",
        "client"
      ]
    },
    {
      "name": "Users",
      "icon": "menu-icon tf-icons bx bx-layout",
      "slug": "layouts",
      "submenu": [
        {
          "url": "users/create",
          "name": "Create User",
          "slug": "content-users-create",
          "roles": [
            "admin"
          ]
        },
        {
          "url": "users",
          "name": "List",
          "slug": "content-users-list",
          "roles": [
            "admin"
          ]
        }
      ],
      "roles": [
        "admin"
      ]
    },
    {
      "name": "Rents (Borrowed Books)",
      "icon": "menu-icon tf-icons bx bx-layout",
      "slug": "layouts",
      "roles": [
        "admin",
        "client"
      ],
      "submenu": [
        {
          "url": "rents/create",
          "name": "Create request",
          "slug": "layouts-without-menu",
          "roles": [
            "client"
          ]
        },
        {
          "url": "rents",
          "name": "List",
          "slug": "layouts-without-navbar",
          "roles": [
            "admin",
            "client"
          ]
        },
        {
          "url": "rents/approval",
          "name": "For Approval",
          "slug": "layouts-without-navbar",
          "roles": [
            "admin"
          ]
        },
        {
          "url": "rents/due-for-return",
          "name": "Due for Return",
          "slug": "content-requests-approval",
          "roles": [
            "admin"
          ]
        }
      ]
    },
    {
      "name": "Books",
      "icon": "menu-icon tf-icons bx bx-layout",
      "slug": "layouts",
      "roles": [
        "admin",
        "client"
      ],
      "submenu": [
        {
          "url": "books/create",
          "name": "Create Book",
          "slug": "layouts-without-menu",
          "roles": [
            "admin"
          ]
        },
        {
          "url": "books",
          "name": "List",
          "slug": "layouts-without-navbar",
          "roles": [
            "admin",
            "client"
          ]
        }
      ]
    }
  ]
}